malevich/__init__.py
malevich/square/__init__.py
malevich_app/__init__.py
malevich_app/requirements.txt
malevich_app/version
malevich_app/docker_dask/__init__.py
malevich_app/docker_dask/export/Interpreter.py
malevich_app/docker_dask/export/__init__.py
malevich_app/docker_dask/export/funcs.py
malevich_app/docker_dask/export/helpers.py
malevich_app/docker_dask/export/operations.py
malevich_app/docker_dask/export/pipeline.py
malevich_app/docker_dask/export/schemes.py
malevich_app/docker_export/Interpreter.py
malevich_app/docker_export/__init__.py
malevich_app/docker_export/funcs.py
malevich_app/docker_export/helpers.py
malevich_app/docker_export/operations.py
malevich_app/docker_export/pipeline.py
malevich_app/docker_export/schemes.py
malevich_app/docker_export_template/__init__.py
malevich_app/docker_export_template/funcs.py
malevich_app/docker_export_template/helpers.py
malevich_app/docker_export_template/operations.py
malevich_app/docker_export_template/pipeline.py
malevich_app/docker_export_template/schemes.py
malevich_app/docker_pyspark/__init__.py
malevich_app/docker_pyspark/export/Interpreter.py
malevich_app/docker_pyspark/export/__init__.py
malevich_app/docker_pyspark/export/funcs.py
malevich_app/docker_pyspark/export/helpers.py
malevich_app/docker_pyspark/export/operations.py
malevich_app/docker_pyspark/export/pipeline.py
malevich_app/docker_pyspark/export/schemes.py
malevich_app/docker_python/__init__.py
malevich_app/export/__init__.py
malevich_app/export/start.py
malevich_app/export/abstract/__init__.py
malevich_app/export/abstract/abstract.py
malevich_app/export/abstract/pipeline.py
malevich_app/export/api/__init__.py
malevich_app/export/api/api.py
malevich_app/export/defaults/__init__.py
malevich_app/export/defaults/schemes.py
malevich_app/export/jls/EntityType.py
malevich_app/export/jls/JuliusApp.py
malevich_app/export/jls/JuliusCollectionHolder.py
malevich_app/export/jls/JuliusPipeline.py
malevich_app/export/jls/JuliusPipelineItem.py
malevich_app-0.3.60.dist-info/licenses/LICENSE
malevich_app-0.3.60.dist-info/METADATA
malevich_app-0.3.60.dist-info/WHEEL
malevich_app-0.3.60.dist-info/top_level.txt
malevich_app-0.3.60.dist-info/RECORD
