Metadata-Version: 2.4
Name: malevich_app
Version: 0.3.60
Author: Andrew Pogrebnoj
Author-email: andrew@malevich.ai
License-File: LICENSE
Requires-Dist: fastapi
Requires-Dist: pydantic
Requires-Dist: pandas
Requires-Dist: uvicorn
Requires-Dist: aiohttp
Requires-Dist: requests
Requires-Dist: kafka-python
Requires-Dist: jsonpickle
Requires-Dist: boto3
Requires-Dist: botocore
Requires-Dist: mypy
Requires-Dist: mypy-extensions
Requires-Dist: typing_extensions
Requires-Dist: pyarrow
Requires-Dist: fastparquet
Requires-Dist: nest-asyncio
Requires-Dist: email-validator
Requires-Dist: malevich_coretools
Requires-Dist: websockets
Dynamic: author
Dynamic: author-email
Dynamic: license-file
Dynamic: requires-dist
